dbr/DBRx64.lib
dbr/DynamicPdfx64.dll
dbr/DynamsoftBarcodeReaderx64.dll
dbr/DynamsoftLicClientx64.dll
dbr/DynamsoftLicenseClientx64.dll
dbr/__init__.py
dbr/dbr.cp311-win_amd64.pyd
dbr/dbr_python.py
dbr/vcomp140.dll
dbr-9.6.60.dist-info/licenses/LICENSE.txt
dbr-9.6.60.dist-info/METADATA
dbr-9.6.60.dist-info/WHEEL
dbr-9.6.60.dist-info/top_level.txt
dbr-9.6.60.dist-info/RECORD
